jaxctx/__init__.py
jaxctx/context.py
jaxctx/priors/__init__.py
jaxctx/priors/prior.py
jaxctx/priors/special_priors.py
jaxctx/priors/types.py
jaxctx/priors/tests/__init__.py
jaxctx/priors/tests/test_prior.py
jaxctx/priors/tests/test_special_priors.py
jaxctx/tests/__init__.py
jaxctx/tests/test_context.py
jaxctx-1.0.4.dist-info/licenses/LICENSE
jaxctx-1.0.4.dist-info/METADATA
jaxctx-1.0.4.dist-info/WHEEL
jaxctx-1.0.4.dist-info/top_level.txt
jaxctx-1.0.4.dist-info/RECORD
