Metadata-Version: 2.4
Name: jaxctx
Version: 1.0.4
Summary: Lightwieght JAX context for managing collections of parameters and RNG sequences.
Author-email: "Joshua G. Albert" <albert@strw.leidenuniv.nl>
License: GNU General Public License v3 (GPLv3)
Project-URL: Homepage, https://github.com/joshuaalbert/jaxctx
Keywords: jax
Classifier: Programming Language :: Python :: 3
Classifier: License :: OSI Approved :: GNU General Public License v3 (GPLv3)
Classifier: Operating System :: OS Independent
Requires-Python: >=3.10
License-File: LICENSE
Dynamic: license-file
